optical_lattice/__init__.py
optical_lattice/analysis_models.py
optical_lattice/deconvolution_analysis.py
optical_lattice/lattice_analyzer.py
optical_lattice/lattice_generation.py
optical_lattice-1.0.dist-info/LICENSE
optical_lattice-1.0.dist-info/METADATA
optical_lattice-1.0.dist-info/WHEEL
optical_lattice-1.0.dist-info/top_level.txt
optical_lattice-1.0.dist-info/RECORD
